{
  "ace2-fm-nc-sfno-c96-v1": "01KX1S62S9PQNTWA4A3WT75QJA",
  "ace2-fm-nc-sfno-c96-v1-bestinfcooldown": "01KX4K2NS5YCQ3V7Y920YPK6RT",
  "ace2-fm-nc-sfno-c96-v1-cooldown": "01KX4GTBHVQPM774QNCTQFJZ24",
  "ace2-fm-nc-sfno-fm-0.1-v1": "01KW39XM9V95FCXRH5YAZH1W5R",
  "ace2-fm-nc-sfno-fm-0.1-v1-bestinfcooldown": "01KX4WNC0HD0QJ77A0NZKM3VMJ",
  "ace2-fm-nc-sfno-fm-0.1-v1-cooldown": "01KX5DYFF3WTF7M7N19KPAXJPG",
  "ace2-fm-nc-sfno-fm-0.5-v1": "01KW39XX4SNTHDDDFDYX01RRY1",
  "ace2-fm-nc-sfno-fm-0.5-v1-bestinfcooldown": "01KX4N9BPM6PD4KSCA38QS45V0",
  "ace2-fm-nc-sfno-fm-0.5-v1-cooldown": "01KX4N9N0GY21TXPSPT1YDERP7",
  "ace2-fm-nc-sfno-fm-0.5-v2": "01KWJK4S43B32AYJZY8C78WZQ8",
  "ace2-fm-nc-sfno-fm-0.5-v2-bestinfcooldown": "01KX5AY1325BVTC0409H45RZG4",
  "ace2-fm-nc-sfno-fm-0.5-v2-cooldown": "01KX4Y0PKJS14C4JG6C7NPA32X",
  "ace2-fm-nc-sfno-fm-0.9-v1": "01KW39Y57HW8R7NAQXCZSDJEP7",
  "ace2-fm-nc-sfno-fm-0.9-v1-bestinfcooldown": "01KX5DZP7NQ7A65ZGAH6JQ36NH",
  "ace2-fm-nc-sfno-fm-0.9-v1-cooldown": "01KX5DZPBJ65P9EQT7K9ZETBBK",
  "ace2-fm-nc-sfno-fm-random-v1": "01KW39YDB8BP1FRGD8C9Z64F10",
  "ace2-fm-nc-sfno-fm-random-v1-bestinfcooldown": "01KX4NB0VG37JS0NQF5RCCA8JY",
  "ace2-fm-nc-sfno-fm-random-v1-cooldown": "01KX4NB98VPGEMGW775Y66DMFX",
  "ace2-fm-nc-sfno-fm-random-v2": "01KX6STB1QPGHEW3EMVCDVEQPW",
  "ace2-fm-nc-sfno-fm-random-v2-bestinfcooldown": "01KXF9T1GHJ2GVRBQZN73QB62H",
  "ace2-fm-nc-sfno-fm-random-v2-cooldown": "01KXEV5YYB8HTGFREE2675SXCG",
  "ace2-fm-nc-sfno-v1": "01KWW006XTJXVA45656N7KFAMX",
  "ace2-fm-nc-sfno-v1-bestinfcooldown": "01KX2G57HB02M7XX9AA5K768ZJ",
  "ace2-fm-nc-sfno-v1-cooldown": "01KX2G57DE6AEP5QB1CTY7KPS9",
  "ace2-fm-nc-sfno-v2": "01KWWXRRV1TJH8GQTQWRA3DWEV",
  "ace2-fm-nc-sfno-v2-bestinfcooldown": "01KX2HF14K0YRH71YSEZ4NACR3",
  "ace2-fm-nc-sfno-v2-cooldown": "01KX2JKZ5GVMK5GJD82621K754",
  "ace2-fm-nc-sfno-c96-v2": "01KX6TB5DK1YE0N1RFE7RHQM9T",
  "ace2-fm-nc-sfno-fm-random-v2-mask10-co2bern80": "01KX6SSW1MW0GXFJX9ZXJNRSME",
  "ace2-fm-nc-sfno-fm-random-v2-old": "01KWJK4ZSCV7Z47PXKGAJS2YNM",
  "ace2-fm-nc-sfno-fm-random-v2-old-bestinfcooldown": "01KX5CP60GVXTY26F07NF0V27P",
  "ace2-fm-nc-sfno-fm-random-v2-old-cooldown": "01KX4X6RTZCCT64SHCDK77K2N7",
  "ace2-fm-nc-sfno-v3": "01KX6TC63B7XV9S3F6NPDP1VHM",
  "ace2-fm-nc-sfno-c96-v2-bestinfcooldown": "01KXFP45TJ6AR92K4XGZ4QDQQA",
  "ace2-fm-nc-sfno-c96-v2-cooldown": "01KXFWKEN2SD1JDMJ80SBCZ9GD",
  "ace2-fm-nc-sfno-v3-bestinfcooldown": "01KXG1BF74HF4RC4VB24FT6FX6",
  "ace2-fm-nc-sfno-v3-cooldown": "01KXG1C1E9H17GRVPK33B3S8C2"
}
